[{"_id": {"$oid": "6352b5c6e4b30dc99f395890"}, "request_endpoint_host": "localhost:33657", "request_endpoint_scheme": "http", "request_endpoint_path": "/views/state", "request_endpoint_method": "GET", "state_id": "6352b5c4e4b30dc99f3957e3", "cluster_count": 3}, {"_id": {"$oid": "6352b5cce4b30dc99f3959f0"}, "request_endpoint_host": "localhost:33657", "request_endpoint_scheme": "http", "request_endpoint_path": "/views/state", "request_endpoint_method": "GET", "state_id": "6352b5c6e4b30dc99f39588f", "cluster_count": 3}]