[{"_id": {"$oid": "63564ff1ceb1823f0c7c20ba"}, "previous_state_id": "No previous state", "caused_by_interaction_id": "No interaction", "revisits": 0, "designator": "", "reachable_from": [], "current": false, "explored": true, "collapsed": false, "fuzzed": true, "initial": true, "hash": "T184218AC82F938D684C1305474A1951C9EF8307BE66E91218A9E1BAC67BEF9473CD4A72", "created_at": 1666600945500}, {"_id": {"$oid": "63564ff3ceb1823f0c7c2166"}, "previous_state_id": "63564ff1ceb1823f0c7c20ba", "caused_by_interaction_id": "63564ff3ceb1823f0c7c2161", "revisits": 0, "designator": "", "reachable_from": [], "current": false, "explored": true, "collapsed": false, "fuzzed": true, "initial": false, "hash": "T1B0218CC82F929D694C1306470A1941C9EF8307BE66E91218A8A1BAC67BEFD473CD4972", "created_at": 1666600947967}, {"_id": {"$oid": "63564ff6ceb1823f0c7c2232"}, "previous_state_id": "63564ff3ceb1823f0c7c2166", "caused_by_interaction_id": "63564ff6ceb1823f0c7c222d", "revisits": 0, "designator": "", "reachable_from": [], "current": true, "explored": true, "collapsed": false, "fuzzed": true, "initial": false, "hash": "T19021CEC82F53DD684C1305470A1951C9EF8307BE66E90258A8A0FAC67AEFD473CD4A72", "created_at": 1666600950992}]