[{"_id": {"$oid": "63527a1534e2c6f03357bf0c"}, "previous_state_id": "No previous state", "caused_by_interaction_id": "No interaction", "revisits": 0, "designator": "", "reachable_from": [], "current": false, "explored": true, "collapsed": false, "fuzzed": true, "initial": true, "hash": "T17541CF5F6C261CF221153BCD1B8654EEC7738B84E63C2F69D84B743B78DE4B69462A20", "created_at": 1666349589028}, {"_id": {"$oid": "63527a1934e2c6f03357bff3"}, "previous_state_id": "63527a1534e2c6f03357bf0c", "caused_by_interaction_id": "63527a1934e2c6f03357bfee", "revisits": 0, "designator": "", "reachable_from": [], "current": false, "explored": true, "collapsed": false, "fuzzed": true, "initial": false, "hash": "T19241C14F6C261CF221193BCD1B8914EEC7738B84E63C2F69D84B742778DE4B69462A60", "created_at": 1666349593590}, {"_id": {"$oid": "63527a2034e2c6f03357c0e0"}, "previous_state_id": "63527a1534e2c6f03357bf0c", "caused_by_interaction_id": "63527a2034e2c6f03357c0db", "revisits": 0, "designator": "", "reachable_from": [], "current": false, "explored": true, "collapsed": false, "fuzzed": true, "initial": false, "hash": "T15941DF4B6C261CF221153BCD2B8654EEC7738B84E23C2F69D84B742778DE4B69462A60", "created_at": 1666349600303}, {"_id": {"$oid": "63527a2834e2c6f03357c1c2"}, "previous_state_id": "63527a1934e2c6f03357bff3", "caused_by_interaction_id": "63527a2834e2c6f03357c1bd", "revisits": 0, "designator": "", "reachable_from": [], "current": false, "explored": true, "collapsed": false, "fuzzed": true, "initial": false, "hash": "T1F641E15F7C261CF221153BCD1B8654EEC7738B84E63C2F29D84B742778DE4B69461A60", "created_at": 1666349608690}, {"_id": {"$oid": "63527a3234e2c6f03357c296"}, "previous_state_id": "63527a1934e2c6f03357bff3", "caused_by_interaction_id": "63527a3234e2c6f03357c291", "revisits": 0, "designator": "", "reachable_from": [], "current": true, "explored": true, "collapsed": false, "fuzzed": true, "initial": false, "hash": "T1A641E25F6C261CF221153BCD1B8A14EEC7738B84E63C2F69D84B742778DE4B69462A10", "created_at": 1666349618352}]