[{"_id": {"$oid": "6352ad6728239972a37ab7d8"}, "request_endpoint_host": "localhost:38485", "request_endpoint_scheme": "http", "request_endpoint_path": "/views/state", "request_endpoint_method": "GET", "state_id": "6352ad6528239972a37ab72b", "cluster_count": 3}, {"_id": {"$oid": "6352ad7128239972a37ab938"}, "request_endpoint_host": "localhost:38485", "request_endpoint_scheme": "http", "request_endpoint_path": "/views/state", "request_endpoint_method": "GET", "state_id": "6352ad6728239972a37ab7d7", "cluster_count": 4}]