[{"_id": {"$oid": "63526cd416beec0e1a18aaa6"}, "request_endpoint_host": "localhost:53151", "request_endpoint_scheme": "http", "request_endpoint_path": "/views/state", "request_endpoint_method": "GET", "state_id": "63526cd116beec0e1a18a9de", "cluster_count": 2}, {"_id": {"$oid": "63526cd916beec0e1a18ab87"}, "request_endpoint_host": "localhost:53151", "request_endpoint_scheme": "http", "request_endpoint_path": "/views/state", "request_endpoint_method": "GET", "state_id": "63526cd416beec0e1a18aaa5", "cluster_count": 2}]